itsme/__init__.py
itsme/itsme.py
itsme/itsme_lib.dll
itsme/itsme_lib.dylib
itsme/itsme_lib.so
itsme-0.0.8.dist-info/METADATA
itsme-0.0.8.dist-info/WHEEL
itsme-0.0.8.dist-info/top_level.txt
itsme-0.0.8.dist-info/RECORD
