Metadata-Version: 2.1
Name: itsme
Version: 0.0.8
Summary: A package to integrate with the itsme OIDC API
Home-page: https://github.com/itsme-api/itsme-api-python
Author: itsme_sdk
Author-email: itsme.store@inthepocket.mobi
License: UNKNOWN
Platform: UNKNOWN
Classifier: Programming Language :: Python :: 3
Classifier: License :: OSI Approved :: MIT License
Classifier: Operating System :: OS Independent
